test_alpha_beta_3_ti_client/__init__.py
test_alpha_beta_3_ti_client/api_client.py
test_alpha_beta_3_ti_client/api_response.py
test_alpha_beta_3_ti_client/configuration.py
test_alpha_beta_3_ti_client/exceptions.py
test_alpha_beta_3_ti_client/py.typed
test_alpha_beta_3_ti_client/rest.py
test_alpha_beta_3_ti_client/api/__init__.py
test_alpha_beta_3_ti_client/api/pet_api.py
test_alpha_beta_3_ti_client/api/store_api.py
test_alpha_beta_3_ti_client/api/user_api.py
test_alpha_beta_3_ti_client/models/__init__.py
test_alpha_beta_3_ti_client/models/address.py
test_alpha_beta_3_ti_client/models/api_response.py
test_alpha_beta_3_ti_client/models/category.py
test_alpha_beta_3_ti_client/models/customer.py
test_alpha_beta_3_ti_client/models/order.py
test_alpha_beta_3_ti_client/models/pet.py
test_alpha_beta_3_ti_client/models/tag.py
test_alpha_beta_3_ti_client/models/user.py
test_alpha_beta_3_ti_client-1.0.0.dist-info/METADATA
test_alpha_beta_3_ti_client-1.0.0.dist-info/WHEEL
test_alpha_beta_3_ti_client-1.0.0.dist-info/top_level.txt
test_alpha_beta_3_ti_client-1.0.0.dist-info/RECORD
